leek/__init__.py
leek/base_queue.py
leek/custom_gevent.py
leek/custom_thread.py
leek/default_config.py
leek/init_config_file.py
leek/kafka_queue.py
leek/memery_queue.py
leek/middleware_eum.py
leek/redis_queue.py
leek/sqllite_queue.py
leek/task_consumer.py
leek/task_publisher.py
leek/test_demo.py
leek/utils.py
redis_queue_tool/RedisQueue.py
redis_queue_tool/__init__.py
redis_queue_tool/base_queue.py
redis_queue_tool/custom_gevent.py
redis_queue_tool/custom_thread.py
redis_queue_tool/default_config.py
redis_queue_tool/init_config_file.py
redis_queue_tool/kafka_queue.py
redis_queue_tool/memery_queue.py
redis_queue_tool/middleware_eum.py
redis_queue_tool/producter_consumer.py
redis_queue_tool/redis_queue.py
redis_queue_tool/sqllite_queue.py
redis_queue_tool/t_redis_queue.py
redis_queue_tool/test_demo.py
redis_queue_tool/utils.py
redis_queue_tool-4.8.7.dist-info/LICENSE.rst
redis_queue_tool-4.8.7.dist-info/METADATA
redis_queue_tool-4.8.7.dist-info/WHEEL
redis_queue_tool-4.8.7.dist-info/top_level.txt
redis_queue_tool-4.8.7.dist-info/RECORD
