Metadata-Version: 2.1
Name: redis-queue-tool
Version: 4.8.7
Summary: 高并发reids队列,分布式爬虫利器(High concurrency RedisQueue,Distributed crawler weapon)
Home-page: https://github.com/abo123456789/redis-queue-tool
Author: cc
Author-email: abcdef123456chen@sohu.com
Maintainer: cc
Maintainer-email: abcdef123456chen@sohu.com
License: MIT License
Keywords: redisqueue,queue-tasks,redis,distributed-scraper,producer-consumer,distribute-crawler,web-crawler
Platform: all
Classifier: Development Status :: 4 - Beta
Classifier: Operating System :: OS Independent
Classifier: Intended Audience :: Developers
Classifier: License :: OSI Approved :: MIT License
Classifier: Programming Language :: Python
Classifier: Programming Language :: Python :: Implementation
Classifier: Programming Language :: Python :: 3.6
Classifier: Topic :: Software Development :: Libraries
Requires-Dist: redis (>=2.10.6)
Requires-Dist: tomorrow3 (>=1.1.0)
Requires-Dist: retrying (>=1.3.3)
Requires-Dist: py-log (>=1.9)
Requires-Dist: persist-queue (>=0.5.0)
Requires-Dist: gevent (>=1.5.0)
Requires-Dist: kafka-python
Requires-Dist: pypattyrn
